<customcontrol>
<version>
459376
</version>
<ccSingleVersionNumber>
1
</ccSingleVersionNumber>
<bank>
29
</bank>
<macro>
10
</macro>
<size>
36
</size>
<name>
GG Relative</name>
<macros offset="0">
<size>
17
</size>
<area>
19
</area>
<me>
0
</me>
<placeholder>
0
</placeholder>
<cmd>
154
</cmd>
<data>
350101020001ff000039</data>
</macros>
<macros offset="19">
<size>
15
</size>
<area>
53
</area>
<me>
0
</me>
<placeholder>
0
</placeholder>
<cmd>
162
</cmd>
<data>
01020001ff000039</data>
</macros>
</customcontrol>
